djtodo_jake0318/File.py
djtodo_jake0318/__init__.py
djtodo_jake0318/djtodo.py
djtodo_jake0318/module.py
djtodo_jake0318/task.json
djtodo_jake0318-0.0.1.dist-info/METADATA
djtodo_jake0318-0.0.1.dist-info/WHEEL
djtodo_jake0318-0.0.1.dist-info/licenses/LICENSE
djtodo_jake0318-0.0.1.dist-info/RECORD
